os_flip/__init__.py
os_flip/__main__.py
os_flip-1.0.5.dist-info/licenses/LICENSE
os_flip-1.0.5.dist-info/METADATA
os_flip-1.0.5.dist-info/WHEEL
os_flip-1.0.5.dist-info/entry_points.txt
os_flip-1.0.5.dist-info/top_level.txt
os_flip-1.0.5.dist-info/RECORD
