Metadata-Version: 2.4
Name: os-flip
Version: 1.0.5
Summary: Cross-platform boot OS selector for Linux, Windows, and macOS
Home-page: https://github.com/AKris15/OS-Flip
Author: AK
Author-email: herogupta626@email.com
License: MIT
Classifier: License :: OSI Approved :: MIT License
Classifier: Operating System :: OS Independent
Classifier: Programming Language :: Python :: 3
Classifier: Environment :: Console
Requires-Python: >=3.6
License-File: LICENSE
Requires-Dist: colorama
Dynamic: author
Dynamic: author-email
Dynamic: classifier
Dynamic: description
Dynamic: description-content-type
Dynamic: home-page
Dynamic: license
Dynamic: license-file
Dynamic: requires-dist
Dynamic: requires-python
Dynamic: summary
